pandus/__init__.py
pandus/pandus.py
pandus-2.1.0.dist-info/LICENSE
pandus-2.1.0.dist-info/METADATA
pandus-2.1.0.dist-info/WHEEL
pandus-2.1.0.dist-info/RECORD
