Metadata-Version: 2.1
Name: pandus
Version: 2.1.0
Summary: A simple wrapper around Pandas
Home-page: https://github.com/egor-georgiev/pandus
License: MIT
Keywords: pandus,pandas,data-science,data-analysis
Author: Egor Georgiev
Requires-Python: >=3.9
Classifier: License :: OSI Approved :: MIT License
Classifier: Programming Language :: Python :: 3
Classifier: Programming Language :: Python :: 3.9
Classifier: Programming Language :: Python :: 3.10
Classifier: Programming Language :: Python :: 3.11
Classifier: Programming Language :: Python :: 3.10
Classifier: Programming Language :: Python :: 3.11
Classifier: Programming Language :: Python :: 3.8
Classifier: Programming Language :: Python :: 3.9
Classifier: Topic :: Scientific/Engineering
Requires-Dist: pandas (==2.1.0)
Project-URL: Repository, https://github.com/egor-georgiev/pandus
